LICENSE
MANIFEST.in
README.rst
setup.py
dedupebackend/__init__.py
dedupebackend/admin.py
dedupebackend/apps.py
dedupebackend/fields.py
dedupebackend/filters.py
dedupebackend/models.py
dedupebackend/settings.py
dedupebackend/storage.py
dedupebackend/utils.py
dedupebackend/migrations/0001_initial.py
dedupebackend/migrations/__init__.py
dedupebackend/static/dedupebackend/uniquefield.css
dedupebackend/templates/dedupebackend/uniquefield.html
dedupebackend/templates/dedupebackend/uniqueimagefield.html
django_dedupe_backend.egg-info/PKG-INFO
django_dedupe_backend.egg-info/SOURCES.txt
django_dedupe_backend.egg-info/dependency_links.txt
django_dedupe_backend.egg-info/namespace_packages.txt
django_dedupe_backend.egg-info/not-zip-safe
django_dedupe_backend.egg-info/requires.txt
django_dedupe_backend.egg-info/top_level.txt