Metadata-Version: 1.0
Name: django-dedupe-backend
Version: 0.0.2
Summary: The super storage backend
Home-page: https://github.com/specialunderwear/django-dedupe-backend
Author: Lars van de Kerkhof
Author-email: lars@permanentmarkers.nl
License: GPL v3
Keywords: django storage backend that stores files in git
Platform: UNKNOWN
